realtime_trains_py/__init__.py
realtime_trains_py/internal/__init__.py
realtime_trains_py/internal/boards.py
realtime_trains_py/internal/details.py
realtime_trains_py/internal/error_handlers.py
realtime_trains_py/internal/live_board.py
realtime_trains_py/internal/services.py
realtime_trains_py/internal/stat_boards.py
realtime_trains_py/internal/utilities.py
realtime_trains_py-2025.3.3.dist-info/METADATA
realtime_trains_py-2025.3.3.dist-info/WHEEL
realtime_trains_py-2025.3.3.dist-info/licenses/LICENSE.md
realtime_trains_py-2025.3.3.dist-info/RECORD
