Metadata-Version: 2.4
Name: realtime-trains-py
Version: 2025.3.3
Summary: Python API Wrapper Package for the Realtime Trains API.
Project-URL: Repository, https://github.com/realtime-trains-lang/realtime-trains-py
Project-URL: Issues, https://github.com/realtime-trains-lang/realtime-trains-py/issues
Project-URL: Discord, https://discord.gg/8xcXSGhBAR
Author-email: anonymous44401 <anonymous4401.ad@gmail.com>
License: MIT License
License-File: LICENSE.md
Classifier: Development Status :: 5 - Production/Stable
Classifier: License :: OSI Approved :: MIT License
Classifier: Operating System :: OS Independent
Classifier: Programming Language :: Python
Requires-Python: >=3.8
Requires-Dist: requests>=2.32.3
Requires-Dist: tabulate>=0.9.0
